minifetch/__init__.py
minifetch/main.py
minifetch-1.0.1.dist-info/licenses/LICENSE
minifetch-1.0.1.dist-info/METADATA
minifetch-1.0.1.dist-info/WHEEL
minifetch-1.0.1.dist-info/entry_points.txt
minifetch-1.0.1.dist-info/top_level.txt
minifetch-1.0.1.dist-info/RECORD
