Metadata-Version: 2.4
Name: minifetch
Version: 1.0.1
Summary: minifetch delivers bite-sized system stats at startup, for those who prefer their uptime with a side of nerdy flair
Author-email: UncleSp1d3r <unclespider@protonmail.com>
License: MIT License
Keywords: system,stats,uptime,fetch
Classifier: Development Status :: 4 - Beta
Classifier: Intended Audience :: Developers
Classifier: License :: OSI Approved :: MIT License
Classifier: Natural Language :: English
Classifier: Programming Language :: Python :: 3.11
Classifier: Programming Language :: Python :: 3.12
Classifier: Programming Language :: Python :: 3.13
Classifier: Programming Language :: Python :: Implementation :: CPython
Classifier: Operating System :: POSIX
Requires-Python: >=3.11
License-File: LICENSE
Requires-Dist: humanize>=4.12.2
Requires-Dist: psutil>=7.0.0
Requires-Dist: pyfiglet>=1.0.2
Requires-Dist: rich>=13.9.4
Requires-Dist: typer>=0.15.2
Dynamic: license-file
